paraqus/__init__.py
paraqus/constants.py
paraqus/paraqusmodel.py
paraqus/writers.py
paraqus/abaqus/__init__.py
paraqus/abaqus/abaqustools.py
paraqus/abaqus/elementlibrary.py
paraqus/abaqus/odbreader.py
paraqus/tests/__init__.py
paraqus/tests/resources/create_element_test_input.py
paraqus/tests/resources/element_test_current.inp
paraqus/tests/resources/element_test_current.odb
paraqus/tests/resources/element_test_old.inp
paraqus/tests/resources/element_test_old.odb
paraqus/tests/resources/pvd_test/int32_pvd_reference.pvd
paraqus/tests/resources/pvd_test/int32_pvtu_reference.pvtu
paraqus/tests/resources/pvd_test/int32_vtu_reference_0.vtu
paraqus/tests/resources/pvd_test/int32_vtu_reference_1.vtu
paraqus/tests/resources/pvd_test/pvd_reference.pvd
paraqus/tests/resources/pvd_test/pvtu_reference.pvtu
paraqus/tests/resources/pvd_test/vtu_reference_0.vtu
paraqus/tests/resources/pvd_test/vtu_reference_1.vtu
paraqus/tests/resources/pvtu_test/int32_pvtu_reference_ascii.pvtu
paraqus/tests/resources/pvtu_test/int32_pvtu_reference_base64.pvtu
paraqus/tests/resources/pvtu_test/int32_pvtu_reference_raw.pvtu
paraqus/tests/resources/pvtu_test/int32_vtu_reference_ascii_0.vtu
paraqus/tests/resources/pvtu_test/int32_vtu_reference_ascii_1.vtu
paraqus/tests/resources/pvtu_test/int32_vtu_reference_base64_0.vtu
paraqus/tests/resources/pvtu_test/int32_vtu_reference_base64_1.vtu
paraqus/tests/resources/pvtu_test/int32_vtu_reference_raw_0.vtu
paraqus/tests/resources/pvtu_test/int32_vtu_reference_raw_1.vtu
paraqus/tests/resources/pvtu_test/pvtu_reference_ascii.pvtu
paraqus/tests/resources/pvtu_test/pvtu_reference_base64.pvtu
paraqus/tests/resources/pvtu_test/pvtu_reference_raw.pvtu
paraqus/tests/resources/pvtu_test/vtu_reference_ascii_0.vtu
paraqus/tests/resources/pvtu_test/vtu_reference_ascii_1.vtu
paraqus/tests/resources/pvtu_test/vtu_reference_base64_0.vtu
paraqus/tests/resources/pvtu_test/vtu_reference_base64_1.vtu
paraqus/tests/resources/pvtu_test/vtu_reference_raw_0.vtu
paraqus-1.0.4.dist-info/LICENSE
paraqus-1.0.4.dist-info/METADATA
paraqus-1.0.4.dist-info/WHEEL
paraqus-1.0.4.dist-info/top_level.txt
paraqus-1.0.4.dist-info/RECORD
