Metadata-Version: 2.1
Name: paraqus
Version: 1.0.4
Summary: VTK file export from Abaqus
Author-email: Tim Furlan <tim.furlan@gmx.de>, Jonathan Stollberg <jonathan.stollberg@tu-dortmund.de>
Classifier: Programming Language :: Python :: 3
Classifier: License :: OSI Approved :: MIT License
Classifier: Operating System :: OS Independent
Requires-Python: >=3.7
License-File: LICENSE
Requires-Dist: numpy
